requestgen/__init__.py
requestgen/code_generator.py
requestgen/converter.py
requestgen/beans/__init__.py
requestgen/beans/http_request.py
requestgen/generator/__init__.py
requestgen/generator/generator.py
requestgen/generator/test.py
requestgen/generator/curl/__init__.py
requestgen/generator/curl/curl_generator.py
requestgen/generator/language_java/__init__.py
requestgen/generator/language_java/apache_http_client.py
requestgen/generator/language_java/http_url_connection.py
requestgen/generator/language_python/__init__.py
requestgen/generator/language_python/python_generator.py
requestgen/parser/__init__.py
requestgen/parser/curl_parser.py
requestgen/parser/parser.py
requestgen-1.5.dist-info/LICENSE
requestgen-1.5.dist-info/METADATA
requestgen-1.5.dist-info/WHEEL
requestgen-1.5.dist-info/entry_points.txt
requestgen-1.5.dist-info/top_level.txt
requestgen-1.5.dist-info/RECORD
