Metadata-Version: 2.1
Name: requestgen
Version: 1.5
Summary: Converter package
Home-page: https://github.com/prajwaldr9/requestgen
Author: Prajwal Ramakrishna
Author-email: prajwaldr9@gmail.com
License: GNU GPL
Keywords: python,first package
Platform: UNKNOWN
Classifier: Development Status :: 5 - Production/Stable
Classifier: Intended Audience :: Developers
Classifier: Topic :: Internet
Classifier: License :: OSI Approved :: GNU General Public License (GPL)
Classifier: Programming Language :: Python :: 3
Classifier: Operating System :: MacOS :: MacOS X
Classifier: Operating System :: Microsoft :: Windows
License-File: LICENSE
